pro_craft/__init__.py
pro_craft/database.py
pro_craft/prompt_craft.py
pro_craft/router/__init__.py
pro_craft/router/models.py
pro_craft/router/prompt.py
pro_craft-0.2.70.dist-info/METADATA
pro_craft-0.2.70.dist-info/WHEEL
pro_craft-0.2.70.dist-info/top_level.txt
pro_craft-0.2.70.dist-info/RECORD
