Metadata-Version: 2.4
Name: pro-craft
Version: 0.2.70
Summary: Add your description here
Requires-Python: >=3.12
Requires-Dist: agno>=2.2.13
Requires-Dist: aiomysql>=0.2.0
Requires-Dist: anyio>=4.11.0
Requires-Dist: db-help>=0.2.2
Requires-Dist: deepagents>=0.2.4
Requires-Dist: fastapi>=0.119.0
Requires-Dist: langchain-openai>=1.0.2
Requires-Dist: mcp[cli]>=1.19.0
Requires-Dist: plotly>=6.3.1
Requires-Dist: psycopg2-binary>=2.9.11
Requires-Dist: pyyaml>=6.0.3
Requires-Dist: toml>=0.10.2
Requires-Dist: uvicorn>=0.38.0
Requires-Dist: woke-time-mcp==0.1.7
